{"name":"parse4cn1 for Parse.com","tagline":"@sidiabale","body":"# Parse4CN1 - Codename One Library for [Parse](https://parse.com) #\r\n\r\n**Ths library is a port of Parse's [REST API](https://www.parse.com/docs/rest) to [CodenameOne](http://www.codenameone.com/) (and by extension to Java).** \r\n\r\n## Useful links ##\r\n* [Information about the library, Parse REST API coverage, how to contribute, etc.](https://github.com/sidiabale/parse4cn1#parse4cn1---codename-one-library-for-parse)\r\n* [Javadoc for parse4cn1](http://sidiabale.github.io/parse4cn1/javadoc) ","google":"","note":"Don't delete this file! It's used internally to help with page regeneration."}